[
  {
    "name": "Brand",
    "name_ar": "العلامة التجارية",
    "settings": [
      {
        "type": "text",
        "id": "brand_name",
        "label": "Brand name",
        "label_ar": "اسم العلامة",
        "default": "",
        "info": "Leave empty to use the store name."
      },
      {
        "type": "text",
        "id": "brand_name_ar",
        "label": "Brand name (Arabic)",
        "label_ar": "اسم العلامة (عربي)",
        "default": ""
      },
      {
        "type": "image_picker",
        "id": "logo_url",
        "label": "Logo",
        "label_ar": "الشعار",
        "info": "Shown in the header. Falls back to the brand name text.",
        "default": ""
      },
      {
        "type": "image_picker",
        "id": "favicon",
        "label": "Favicon (browser tab icon)",
        "label_ar": "أيقونة المتصفح",
        "default": ""
      },
      {
        "type": "color",
        "id": "primary_color",
        "label": "Ink (primary)",
        "label_ar": "اللون الأساسي (الحبر)",
        "default": "#1A1A1A",
        "info": "Buttons, footer, active states. Near-black by default."
      },
      {
        "type": "color",
        "id": "accent_color",
        "label": "Gold accent",
        "label_ar": "لون التمييز (الذهبي)",
        "default": "#B8860B"
      },
      {
        "type": "color",
        "id": "background_color",
        "label": "Canvas background",
        "label_ar": "لون الخلفية",
        "default": "#FFFFFF"
      },
      {
        "type": "color",
        "id": "text_color",
        "label": "Body text",
        "label_ar": "لون النص",
        "default": "#1A1A1A"
      }
    ]
  },
  {
    "name": "Typography",
    "name_ar": "الخطوط",
    "settings": [
      {
        "type": "select",
        "id": "heading_font",
        "label": "Heading font",
        "label_ar": "خط العناوين",
        "default": "inter",
        "info": "Headings stay uppercase with wide letter-spacing — the luxury-minimal signature.",
        "options": [
          { "value": "inter", "label": "Inter (clean sans)", "label_ar": "إنتر" },
          { "value": "montserrat", "label": "Montserrat (display)", "label_ar": "مونتسيرات" },
          { "value": "poppins", "label": "Poppins (geometric)", "label_ar": "بوبينز" },
          { "value": "cairo", "label": "Cairo (Arabic-first)", "label_ar": "القاهرة" }
        ]
      },
      {
        "type": "select",
        "id": "body_font",
        "label": "Body font",
        "label_ar": "خط النص",
        "default": "inter",
        "options": [
          { "value": "inter", "label": "Inter (clean sans)", "label_ar": "إنتر" },
          { "value": "montserrat", "label": "Montserrat", "label_ar": "مونتسيرات" },
          { "value": "cairo", "label": "Cairo (Arabic-first)", "label_ar": "القاهرة" },
          { "value": "tajawal", "label": "Tajawal (Arabic-first)", "label_ar": "تجوال" }
        ]
      }
    ]
  },
  {
    "name": "Layout",
    "name_ar": "التخطيط",
    "settings": [
      {
        "type": "range",
        "id": "corner_radius",
        "label": "Corner radius",
        "label_ar": "استدارة الزوايا",
        "default": 0,
        "min": 0,
        "max": 24,
        "step": 1,
        "unit": "px",
        "info": "Luxury Minimal uses sharp edges (0) by default."
      }
    ]
  },
  {
    "name": "Social links",
    "name_ar": "روابط التواصل",
    "settings": [
      {
        "type": "url",
        "id": "social_instagram",
        "label": "Instagram URL",
        "label_ar": "رابط إنستجرام",
        "default": ""
      },
      {
        "type": "url",
        "id": "social_facebook",
        "label": "Facebook URL",
        "label_ar": "رابط فيسبوك",
        "default": ""
      },
      {
        "type": "url",
        "id": "social_tiktok",
        "label": "TikTok URL",
        "label_ar": "رابط تيك توك",
        "default": ""
      },
      {
        "type": "url",
        "id": "social_x",
        "label": "X (Twitter) URL",
        "label_ar": "رابط إكس (تويتر)",
        "default": ""
      },
      {
        "type": "url",
        "id": "social_whatsapp",
        "label": "WhatsApp number or link",
        "label_ar": "رقم أو رابط واتساب",
        "default": ""
      },
      {
        "type": "url",
        "id": "social_youtube",
        "label": "YouTube URL",
        "label_ar": "رابط يوتيوب",
        "default": ""
      }
    ]
  }
]
